Metadata-Version: 2.1
Name: invoicing-pdf-ln
Version: 1.0.0
Summary: This package is designed for the conversion of Excel invoices into PDF invoices.
Home-page: https://example.com
Author: Paul Lennard Polito
Author-email: lennardpolito@gmail.com
License: MIT
Keywords: invoice,excel,pdf
Classifier: Development Status :: 3 - Alpha
Classifier: Intended Audience :: Developers
Classifier: Topic :: Software Development :: Build Tools
Classifier: License :: OSI Approved :: MIT License
Classifier: Programming Language :: Python :: 3.8
Classifier: Programming Language :: Python :: 3.9
Classifier: Programming Language :: Python :: 3.10
Classifier: Programming Language :: Python :: 3.11
